{"namedChunkGroups":{"polyfill":{"name":"polyfill","assets":[{"name":"webpack-runtime-df92ce027ddb9f0ace81.js","size":3848},{"name":"polyfill-47d3163ed88a083b1e2c.js","size":82648}],"filteredAssets":0,"assetsSize":86496,"filteredAuxiliaryAssets":2,"auxiliaryAssetsSize":216892},"app":{"name":"app","assets":[{"name":"webpack-runtime-df92ce027ddb9f0ace81.js","size":3848},{"name":"framework-f4d564d09974c60e1b27.js","size":129923},{"name":"app-60d6a02f523c84d95499.js","size":111694}],"filteredAssets":0,"assetsSize":245465,"filteredAuxiliaryAssets":3,"auxiliaryAssetsSize":850699},"component---src-pages-404-tsx":{"name":"component---src-pages-404-tsx","assets":[{"name":"component---src-pages-404-tsx-6a0ea0d7497b80f3c68d.js","size":355}],"filteredAssets":0,"assetsSize":355,"filteredAuxiliaryAssets":1,"auxiliaryAssetsSize":430},"component---src-pages-index-tsx":{"name":"component---src-pages-index-tsx","assets":[{"name":"component---src-pages-index-tsx-b45343841e8aadacc4e5.js","size":358}],"filteredAssets":0,"assetsSize":358,"filteredAuxiliaryAssets":1,"auxiliaryAssetsSize":428},"component---src-templates-resume-index-tsx":{"name":"component---src-templates-resume-index-tsx","assets":[{"name":"0f1ac474-271e6efeba0f18e8e00a.js","size":70891},{"name":"component---src-templates-resume-index-tsx-6b4b5b02e71eabca962a.js","size":40301}],"filteredAssets":0,"assetsSize":111192,"filteredAuxiliaryAssets":2,"auxiliaryAssetsSize":534894}},"assetsByChunkName":{"polyfill":["webpack-runtime-df92ce027ddb9f0ace81.js","polyfill-47d3163ed88a083b1e2c.js"],"app":["webpack-runtime-df92ce027ddb9f0ace81.js","framework-f4d564d09974c60e1b27.js","app-60d6a02f523c84d95499.js"],"component---src-pages-404-tsx":["component---src-pages-404-tsx-6a0ea0d7497b80f3c68d.js"],"component---src-pages-index-tsx":["component---src-pages-index-tsx-b45343841e8aadacc4e5.js"],"component---src-templates-resume-index-tsx":["0f1ac474-271e6efeba0f18e8e00a.js","component---src-templates-resume-index-tsx-6b4b5b02e71eabca962a.js"]},"childAssetsByChunkName":{}}